{
  "resourceType": "ValueSet",
  "status": "active",
  "name": "EndpointVisibilityVS",
  "id": "EndpointVisibilityVS",
  "title": "EndpointVisibilityVS",
  "description": "EndpointVisibilityVS",
  "version": "1.1.0",
  "url": "https://gematik.de/fhir/directory/ValueSet/EndpointVisibilityVS",
  "experimental": false,
  "publisher": "gematik GmbH",
  "date": "2025-02-26",
  "compose": {
    "include": [
      {
        "system": "https://gematik.de/fhir/directory/CodeSystem/EndpointVisibilityCS"
      }
    ]
  }
}
